sphinxlint/__init__.py
sphinxlint/__main__.py
sphinxlint/checkers.py
sphinxlint/cli.py
sphinxlint/rst.py
sphinxlint/sphinxlint.py
sphinxlint/utils.py
sphinx_lint-0.9.1.dist-info/METADATA
sphinx_lint-0.9.1.dist-info/WHEEL
sphinx_lint-0.9.1.dist-info/entry_points.txt
sphinx_lint-0.9.1.dist-info/licenses/LICENSE
sphinx_lint-0.9.1.dist-info/RECORD
