Metadata-Version: 2.1
Name: sphinx-lint
Version: 0.9.1
Summary: Check for stylistic and formal issues in .rst and .py files included in the documentation.
Project-URL: Changelog, https://github.com/sphinx-contrib/sphinx-lint/releases
Project-URL: Repository, https://github.com/sphinx-contrib/sphinx-lint
Author-email: Georg Brandl <georg@python.org>, Julien Palard <julien@palard.fr>
License: PSF License
License-File: LICENSE
Classifier: Development Status :: 5 - Production/Stable
Classifier: Intended Audience :: Developers
Classifier: License :: OSI Approved :: Python Software Foundation License
Classifier: Natural Language :: English
Classifier: Programming Language :: Python :: 3 :: Only
Classifier: Programming Language :: Python :: 3.8
Classifier: Programming Language :: Python :: 3.9
Classifier: Programming Language :: Python :: 3.10
Classifier: Programming Language :: Python :: 3.11
Classifier: Programming Language :: Python :: 3.12
Classifier: Programming Language :: Python :: 3.13
Classifier: Topic :: Documentation :: Sphinx
Requires-Python: >=3.8
Requires-Dist: polib
Requires-Dist: regex
Provides-Extra: tests
Requires-Dist: pytest; extra == 'tests'
Requires-Dist: pytest-cov; extra == 'tests'
